{
  "file": "./models/readings.json",
  "readings": [
    {
      "code": 500,
      "temperature": 30,
      "windspeed": 12,
      "pressure": 1,
      "_id": "520455a0-2706-403b-abdf-70d1f318b132",
      "stationid": "b4febb51-7aa5-4b87-9121-9f107d5e40e5"
    },
    {
      "code": 400,
      "temperature": 2,
      "windspeed": 2,
      "pressure": 2,
      "_id": "993b5c93-3c69-4266-a01f-330f4abbc0d8",
      "stationid": "b4febb51-7aa5-4b87-9121-9f107d5e40e5"
    },
    {
      "code": 200,
      "temperature": 30,
      "windspeed": 25,
      "pressure": 1000,
      "_id": "118beeea-c07c-49be-9d7e-0da010e5f840",
      "stationid": "b4febb51-7aa5-4b87-9121-9f107d5e40e5"
    },
    {
      "code": 400,
      "temperature": 40,
      "fahrenheit": 104,
      "windchill": 47.64,
      "windspeed": 120,
      "beaufort": 0,
      "winddirection": 45,
      "pressure": 33,
      "_id": "6dbffdbd-26bf-4618-be9d-e910fbad9690",
      "stationid": "e3796c78-174e-4e4b-b5cd-1ef50106697d"
    }
  ]
}