{
  "file": "./models/readings.json",
  "readings": [
    {
      "code": 800,
      "temperature": 0.5,
      "windspeed": 3.5,
      "winddirection": 90,
      "pressure": 1002,
      "dateTime": "25/04/2021 07:20:42",
      "_id": "6999a8b9-620c-4198-8a69-db3a081d9623",
      "stationid": "aab9d250-79e0-4576-a7ea-4646ce462624"
    },
    {
      "code": 600,
      "temperature": 6,
      "windspeed": 2,
      "winddirection": 96,
      "pressure": 1004,
      "dateTime": "25/05/2021 07:20:42",
      "_id": "394ec3d1-2f0b-4b36-be10-ce3270febb1d",
      "stationid": "aab9d250-79e0-4576-a7ea-4646ce462624"
    },
    {
      "code": 700,
      "temperature": 8,
      "windspeed": 1,
      "winddirection": 101,
      "pressure": 1005,
      "dateTime": "25/06/2021 07:20:42",
      "_id": "fdeab619-2973-48c7-ad6a-3013007cfe90",
      "stationid": "aab9d250-79e0-4576-a7ea-4646ce462624"
    },
    {
      "code": 700,
      "temperature": 8,
      "windspeed": 1,
      "winddirection": 98,
      "pressure": 999,
      "dateTime": "25/02/2021 07:20:42",
      "_id": "3fa6921c-40b1-41ec-9336-85fbf5843635",
      "stationid": "91d2e26d-77ae-4e18-8277-adec496701c1"
    },
    {
      "code": 200,
      "temperature": 0.5,
      "windspeed": 3.5,
      "winddirection": 102,
      "pressure": 1000,
      "dateTime": "25/03/2021 07:20:42",
      "_id": "ff3b282e-3d42-4471-8889-be465ab0def0",
      "stationid": "91d2e26d-77ae-4e18-8277-adec496701c1"
    },
    {
      "code": 500,
      "temperature": 1,
      "windspeed": 25,
      "winddirection": 90,
      "pressure": 999,
      "dateTime": "9/8/2023 12:57:27",
      "_id": "68045f60-f857-46d5-b92c-23b2a1d5979e",
      "stationid": "140d5673-295b-4354-ad70-512099cd2510"
    },
    {
      "code": 800,
      "temperature": 8,
      "windspeed": 14,
      "winddirection": 99,
      "pressure": 1000,
      "dateTime": "9/8/2023 13:32:49",
      "_id": "8142cf4b-4f7f-4e6b-bfdc-25efb2773536",
      "stationid": "140d5673-295b-4354-ad70-512099cd2510"
    },
    {
      "code": 100,
      "temperature": 30,
      "windspeed": 14,
      "winddirection": 345,
      "pressure": 1005,
      "dateTime": "9/8/2023 13:42:17",
      "_id": "37cd7c8d-a6f6-4ca2-adf9-109b7f909b2e",
      "stationid": "140d5673-295b-4354-ad70-512099cd2510"
    },
    {
      "code": 700,
      "temperature": 0,
      "windspeed": 12,
      "winddirection": 100,
      "pressure": 1000,
      "dateTime": "11/8/2023 12:05:17",
      "_id": "5c599f08-eb64-4c04-9074-b2e580a60c4d",
      "stationid": "91d2e26d-77ae-4e18-8277-adec496701c1"
    },
    {
      "code": 800,
      "temperature": 18.02,
      "windspeed": 7.13,
      "winddirection": 229,
      "pressure": 1013,
      "dateTime": "12/8/2023 21:34:09",
      "_id": "f0ef3f38-1fda-4286-a4bc-47ceaffc1b00",
      "stationid": "140d5673-295b-4354-ad70-512099cd2510"
    },
    {
      "code": 804,
      "temperature": 18.39,
      "windspeed": 3.61,
      "winddirection": 233,
      "pressure": 1017,
      "dateTime": "12/8/2023 21:34:55",
      "_id": "6b549cf4-8907-4efa-8f5a-7dfb824d22d8",
      "stationid": "085df8a2-4c06-45ae-95ab-fcff53981a7d"
    },
    {
      "code": 804,
      "temperature": 18.39,
      "windspeed": 3.61,
      "winddirection": 233,
      "pressure": 1017,
      "dateTime": "12/8/2023 21:36:46",
      "_id": "66fee91d-2a7a-4f44-9a65-e642c255f0e2",
      "stationid": "085df8a2-4c06-45ae-95ab-fcff53981a7d"
    },
    {
      "code": 803,
      "temperature": 17.83,
      "windspeed": 8.37,
      "winddirection": 223,
      "pressure": 1014,
      "dateTime": "13/8/2023 12:13:48",
      "_id": "4fb12c07-1845-4507-9516-c7d392ac5798",
      "stationid": "140d5673-295b-4354-ad70-512099cd2510"
    },
    {
      "code": 804,
      "temperature": 22.71,
      "windspeed": 5.1,
      "winddirection": 212,
      "pressure": 1016,
      "dateTime": "13/8/2023 12:19:37",
      "_id": "105edf8b-fb89-463f-8e9f-5ddfb615c50c",
      "stationid": "085df8a2-4c06-45ae-95ab-fcff53981a7d"
    },
    {
      "code": 804,
      "temperature": 14.88,
      "windspeed": 3.75,
      "winddirection": 236,
      "pressure": 1010,
      "dateTime": "13/8/2023 13:24:07",
      "_id": "8fb99a8b-bd2b-4abd-ad4b-6f2475e0dc41",
      "stationid": "61a84008-b9b8-4610-b18d-6c003aeca9da"
    },
    {
      "code": 803,
      "temperature": 18.02,
      "windspeed": 8.15,
      "winddirection": 223,
      "pressure": 1014,
      "dateTime": "13/8/2023 13:26:16",
      "_id": "c415ad5a-97a5-48a2-8e7a-5f3536735d13",
      "stationid": "140d5673-295b-4354-ad70-512099cd2510"
    },
    {
      "code": 804,
      "temperature": 14.88,
      "windspeed": 1.2,
      "winddirection": 39,
      "pressure": 1008,
      "dateTime": "13/8/2023 20:50:28",
      "_id": "3d6ba1b0-bac7-4bf0-84f7-b1522fc912a5",
      "stationid": "61a84008-b9b8-4610-b18d-6c003aeca9da"
    },
    {
      "code": 804,
      "temperature": 17.1,
      "windspeed": 6.82,
      "winddirection": 110,
      "pressure": 1003,
      "dateTime": "18/8/2023 12:27:02",
      "_id": "15ce7fcf-3cb5-4f1b-8302-9d9d7ecf0b55",
      "stationid": "61a84008-b9b8-4610-b18d-6c003aeca9da"
    }
  ]
}